{"cameraMode":{"drawMode":0,"name":"Shaded","section":"Shading Mode"},"sceneLighting":true,"audioPlay":false,"sceneViewState":{"showFog":true,"showMaterialUpdate":false,"showSkybox":true,"showFlares":true,"showImageEffects":true,"showParticleSystems":true},"in2DMode":false,"pivot":{"x":-6.070000171661377,"y":-1.229712963104248,"z":15.3100004196167},"rotation":{"x":0.2877129018306732,"y":-0.21816669404506684,"z":0.06748140603303909,"w":0.9300918579101563},"size":45.438961029052737,"orthographic":false}